{"i":{"ggxbriOfgN":{"id":"ggxbriOfgN","type":"slide","setup":{"transparentBg":{"selectedKey":false},"bord":{"size":0,"rad":0},"bg":{"selectedKey":"fill","fill":{"opac":1,"rgb":"var(--TC3)"}}}},"_A4pcz2bt":{"id":"_A4pcz2bt","type":"interactive","subtype":"interactiveABC","setup":{"cover":{"selectedKey":"image","fill":{"opac":1,"rgb":"#FFF"},"gradient":{"angle":0,"opac":1,"stops":[{"color":"#000000","pos":0},{"color":"#000000","pos":100}]},"img":{"filt":{"opac":100,"gray":0,"blur":0,"tint":{"rgb":"var(--TC13)","opac":0.7}},"pos":{"type":"crop","fit":{"bg":{"color":{"rgb":"#FFF","opac":100},"gradient":{"angle":0,"opac":0.5,"stops":[{"color":"#000000","pos":0},{"color":"#000000","pos":100}]}},"vali":"center","hali":"center"},"crop":{"bg":{"color":{"rgb":"var(--TC13)","opac":0},"gradient":{"angle":0,"opac":0.5,"stops":[{"color":"#000000","pos":0},{"color":"#000000","pos":100}]}},"poi":{"x":515,"y":182}},"mask":{"shape":1,"bg":{"color":{"rgb":"#FFF","opac":0},"gradient":{"angle":0,"opac":0.5,"stops":[{"color":"#000000","pos":0},{"color":"#000000","pos":100}]}}},"zoom":0},"measures":{"size":{"width":978,"height":649}},"orig":{"rType":"asset","rSubType":"image","fileName":"afianzando lo aprendido2.PNG","fileSize":805684,"val":"mc-e6ee7480b64eb3848150d712a50c8c59.PNG","aid":"mAMWEKRDO"}}},"desc":{"rType":"text","tag":"p","val":"Afianzando lo aprendido"},"answerMode":{"selectedKey":"single"},"quest":{"i":{"aqSLgflkk":{"type":"question","id":"aqSLgflkk","text":{"rType":"text","val":"¿Philip B. Crosby propuso los Cinco Absolutos de la Calidad, incluyendo \"La calidad es cumplimiento\"?​"},"answ":{"i":{"5CkIHowR1":{"type":"answer","id":"5CkIHowR1","text":{"rType":"text","val":"Falso"}},"Goc6iVrt1":{"type":"answer","id":"Goc6iVrt1","text":{"rType":"text","val":"Verdadero"}}},"p":["5CkIHowR1","Goc6iVrt1"],"corrects":["Goc6iVrt1"]}},"JUVO8HPn7":{"type":"question","id":"JUVO8HPn7","text":{"rType":"text","val":"¿Walter A. Shewhart es considerado el padre de las teorías modernas de la gestión de la calidad?"},"answ":{"i":{"qFd0cOYEC":{"type":"answer","id":"qFd0cOYEC","text":{"rType":"text","val":"Verdadero"}},"78oZ1t4E0":{"type":"answer","id":"78oZ1t4E0","text":{"rType":"text","val":"Falso"}}},"p":["78oZ1t4E0","qFd0cOYEC"],"corrects":["qFd0cOYEC"]}},"jt5fyKuiG":{"type":"question","id":"jt5fyKuiG","text":{"rType":"text","val":"¿Kaoru Ishikawa es conocido por su trabajo en la industria de la automoción?"},"answ":{"i":{"rKu2caqBI":{"type":"answer","id":"rKu2caqBI","text":{"rType":"text","val":"Verdadero"}},"NFwt53CvW":{"type":"answer","id":"NFwt53CvW","text":{"rType":"text","val":"Falso"}}},"p":["NFwt53CvW","rKu2caqBI"],"corrects":["NFwt53CvW"]}},"sP9m99kFs":{"type":"question","id":"sP9m99kFs","text":{"rType":"text","val":"¿W. Edwards Deming estableció el Premio Crosby en honor a sus contribuciones?​"},"answ":{"i":{"HsJ3uXan-":{"type":"answer","id":"HsJ3uXan-","text":{"rType":"text","val":"Falso"}},"UVemQVpAj":{"type":"answer","id":"UVemQVpAj","text":{"rType":"text","val":"Verdadero"}}},"p":["HsJ3uXan-","UVemQVpAj"],"corrects":["HsJ3uXan-"]}},"JepLrwG0P":{"type":"question","id":"JepLrwG0P","text":{"rType":"text","val":"¿Philip B. Crosby sostiene que la definición de la calidad debe ser en términos internos de la organización?​"},"answ":{"i":{"yhtmKYQke":{"type":"answer","id":"yhtmKYQke","text":{"rType":"text","val":"Falso"}},"tonXv4JXY":{"type":"answer","id":"tonXv4JXY","text":{"rType":"text","val":"Verdadero"}}},"p":["yhtmKYQke","tonXv4JXY"],"corrects":["yhtmKYQke"]}},"EoGzio6oI":{"type":"question","id":"EoGzio6oI","text":{"rType":"text","val":"¿Joseph M. Juran se enfocó en la Planificación de la Calidad, Control de la Calidad y Mejora de la Calidad en su trilogía?"},"answ":{"i":{"_mlNKjc8d":{"type":"answer","id":"_mlNKjc8d","text":{"rType":"text","val":"Verdadero"}},"PbqugjecA-":{"type":"answer","id":"PbqugjecA-","text":{"rType":"text","val":"Falso"}}},"p":["PbqugjecA-","_mlNKjc8d"],"corrects":["_mlNKjc8d"]}},"lTpzjJZqv":{"type":"question","id":"lTpzjJZqv","text":{"rType":"text","val":"¿Shigeo Shingo desarrolló el Sistema SMED para reducir el tiempo de cambio de herramientas en la producción?​"},"answ":{"i":{"qRm0DqvRn":{"type":"answer","id":"qRm0DqvRn","text":{"rType":"text","val":"Falso"}},"KKhXagRj0":{"type":"answer","id":"KKhXagRj0","text":{"rType":"text","val":"Verdadero"}}},"p":["qRm0DqvRn","KKhXagRj0"],"corrects":["KKhXagRj0"]}},"NjMnM6LP9":{"type":"question","id":"NjMnM6LP9","text":{"rType":"text","val":"¿Genichi Taguchi es conocido por su trabajo en la teoría de la información?"},"answ":{"i":{"7wSvet8t5":{"type":"answer","id":"7wSvet8t5","text":{"rType":"text","val":"Falso"}},"2jgCNo9Cq":{"type":"answer","id":"2jgCNo9Cq","text":{"rType":"text","val":"Verdadero"}}},"p":["7wSvet8t5","2jgCNo9Cq"],"corrects":["7wSvet8t5"]}},"_KLZP4s8W":{"type":"question","id":"_KLZP4s8W","text":{"rType":"text","val":"¿Shigeo Shingo es conocido por su contribución a la industria de la moda?​"},"answ":{"i":{"K5wrXRlFL":{"type":"answer","id":"K5wrXRlFL","text":{"rType":"text","val":"Falso"}},"7HbyN8pwo":{"type":"answer","id":"7HbyN8pwo","text":{"rType":"text","val":"Verdadero"}}},"p":["K5wrXRlFL","7HbyN8pwo"],"corrects":["K5wrXRlFL"]}},"SIMQFeTNI":{"type":"question","id":"SIMQFeTNI","text":{"rType":"text","val":"¿Armand V. Feigenbaum es considerado uno de los principales exponentes del Sistema de Producción Toyota?​"},"answ":{"i":{"WekmEafc4":{"type":"answer","id":"WekmEafc4","text":{"rType":"text","val":"Falso"}},"g52XtMsix":{"type":"answer","id":"g52XtMsix","text":{"rType":"text","val":"Verdadero"}}},"p":["WekmEafc4","g52XtMsix"],"corrects":["WekmEafc4"]}},"1_M_96Wu2":{"type":"question","id":"1_M_96Wu2","text":{"rType":"text","val":"¿Armand V. Feigenbaum desarrolló el concepto de Control Total de la Calidad (CTC)?​"},"answ":{"i":{"aIwmnjqgK":{"type":"answer","id":"aIwmnjqgK","text":{"rType":"text","val":"Verdadero"}},"IMZXRj7Br":{"type":"answer","id":"IMZXRj7Br","text":{"rType":"text","val":"Falso"}}},"p":["IMZXRj7Br","aIwmnjqgK"],"corrects":["aIwmnjqgK"]}},"DQShh16E2":{"type":"question","id":"DQShh16E2","text":{"rType":"text","val":"¿Kaoru Ishikawa desarrolló el diagrama de Ishikawa, también conocido como diagrama de causa y efecto?​"},"answ":{"i":{"gNg0t0qos":{"type":"answer","id":"gNg0t0qos","text":{"rType":"text","val":"Falso"}},"ThUsPLCVe":{"type":"answer","id":"ThUsPLCVe","text":{"rType":"text","val":"Verdadero"}}},"p":["gNg0t0qos","ThUsPLCVe"],"corrects":["ThUsPLCVe"]}},"RaGNNCQpe":{"type":"question","id":"RaGNNCQpe","text":{"rType":"text","val":"¿W. Edwards Deming argumentó que el 85% de los problemas de calidad en las empresas se deben a la gestión de la dirección?"},"answ":{"i":{"8BF850hqK":{"type":"answer","id":"8BF850hqK","text":{"rType":"text","val":"Falso"}},"BTCswsDxK":{"type":"answer","id":"BTCswsDxK","text":{"rType":"text","val":"Verdadero"}}},"p":["8BF850hqK","BTCswsDxK"],"corrects":["BTCswsDxK"]}},"Ac4X7CmVZ":{"type":"question","id":"Ac4X7CmVZ","text":{"rType":"text","val":"¿Walter A. Shewhart desarrolló el Control Estadístico de la Calidad en 1940?"},"answ":{"i":{"4UwLFkq3-":{"type":"answer","id":"4UwLFkq3-","text":{"rType":"text","val":"Falso"}},"GQymIqLmb":{"type":"answer","id":"GQymIqLmb","text":{"rType":"text","val":"Verdadero"}}},"p":["4UwLFkq3-","GQymIqLmb"],"corrects":["4UwLFkq3-"]}}},"p":["JUVO8HPn7","Ac4X7CmVZ","RaGNNCQpe","sP9m99kFs","EoGzio6oI","JepLrwG0P","aqSLgflkk","jt5fyKuiG","DQShh16E2","SIMQFeTNI","1_M_96Wu2","_KLZP4s8W","lTpzjJZqv","NjMnM6LP9"]}}}},"v":"1"}